mockoauthserver/apiclient.py
mockoauthserver/server.py
mockoauthserver-4.7.dist-info/licenses/LICENSE
mockoauthserver-4.7.dist-info/METADATA
mockoauthserver-4.7.dist-info/WHEEL
mockoauthserver-4.7.dist-info/top_level.txt
mockoauthserver-4.7.dist-info/RECORD
