Metadata-Version: 2.4
Name: mockoauthserver
Version: 4.7
Summary: Library for _uois project.
Home-page: https://github.com/hrbolek/PyMockOAuthServer
Author: Profesor Hrbolek
Author-email: profesor@hrbolek.cz
License: MIT
Classifier: Development Status :: 3 - Alpha
Classifier: License :: OSI Approved :: MIT License
Classifier: Programming Language :: Python :: 3.8
Classifier: Programming Language :: Python :: 3.9
Classifier: Topic :: Database
License-File: LICENSE
Requires-Dist: fastapi
Requires-Dist: python-multipart
Requires-Dist: pyjwt[crypto]
Requires-Dist: cryptography
Dynamic: author
Dynamic: author-email
Dynamic: classifier
Dynamic: home-page
Dynamic: license
Dynamic: license-file
Dynamic: requires-dist
Dynamic: summary
